{"legislative_session": "2026", "identifier": "HB 1355", "title": "Rent Reporting to Credit Reporting Agencies", "from_organization": "~{\"classification\": \"lower\"}", "classification": ["bill"], "subject": ["subject index"], "abstracts": [{"note": "summary", "abstract": "Rent Reporting to Credit Reporting Agencies;  Authorizes landlord to report tenant's rent payment history to credit reporting agencies under certain conditions; requires tenant to provide written consent to participate in rent reporting; provides requirements for such consent form; authorizes tenant to opt out of rent reporting at any time without penalty; provides notice requirements; authorizes landlord to charge specified fee for providing rent reporting services; prohibits landlord from taking certain actions; authorizes landlord to stop reporting tenant's rental payments; prohibits tenant from participating in rent reporting for specified amount of time; prohibits landlord from taking retaliatory actions if tenant refuses, declines, or opts out of rent reporting."}], "other_titles": [], "other_identifiers": [], "actions": [{"description": "Filed", "date": "2026-01-09", "organization_id": "~{\"classification\": \"lower\"}", "classification": ["filing"], "related_entities": []}, {"description": "1st Reading (Original Filed Version)", "date": "2026-01-13", "organization_id": "~{\"classification\": \"lower\"}", "classification": ["filing", "reading-1"], "related_entities": []}, {"description": "Referred to Civil Justice & Claims Subcommittee", "date": "2026-01-15", "organization_id": "~{\"classification\": \"lower\"}", "classification": ["referral-committee"], "related_entities": []}, {"description": "Referred to Housing, Agriculture & Tourism Subcommittee", "date": "2026-01-15", "organization_id": "~{\"classification\": \"lower\"}", "classification": ["referral-committee"], "related_entities": []}, {"description": "Referred to Judiciary Committee", "date": "2026-01-15", "organization_id": "~{\"classification\": \"lower\"}", "classification": ["referral-committee"], "related_entities": []}, {"description": "Now in Civil Justice & Claims Subcommittee", "date": "2026-01-15", "organization_id": "~{\"classification\": \"lower\"}", "classification": [], "related_entities": []}], "sponsorships": [{"name": "Rayner", "classification": "primary", "entity_type": "person", "primary": true, "person_id": "~{\"name\": \"Rayner\"}", "organization_id": null}], "related_bills": [], "versions": [{"note": "H 1355 Filed", "links": [{"url": "https://flsenate.gov/Session/Bill/2026/1355/BillText/Filed/PDF", "media_type": "application/pdf"}], "date": "", "classification": ""}], "documents": [], "citations": [], "sources": [{"url": "https://flsenate.gov/Session/Bill/2026/1355/ByCategory", "note": ""}], "extras": {}, "jurisdiction": {"id": "ocd-jurisdiction/country:us/state:fl/government", "name": "Florida", "classification": "state", "division_id": "ocd-division/country:us/state:fl"}, "scraped_at": "2026-01-31T12:14:31+00:00", "_id": "041cceaa-fe98-11f0-a93d-ce2a7d54be4b"}