{"legislative_session": "2026", "identifier": "HB 607", "title": "Industries and Professional Activities", "from_organization": "~{\"classification\": \"lower\"}", "classification": ["bill"], "subject": ["executive branch", "industry", "insurance", "labor", "ports and harbors", "public lands and property", "public transportation", "reclamation, and use", "regulation of professions and occupations", "subject index", "vessels"], "abstracts": [{"note": "summary", "abstract": "Industries and Professional Activities;  Renames, removes, & redesignates specified boards, commissions, and councils established within DBPR; changes office locations of certain divisions; specifies that certain license application requirements apply only to certain professions;  provides licensing authority to department rather than licensing boards; removes postlicensure education requirements for brokers, broker associates, and sales associates; removes continuing education requirements for licensure renewal as broker, broker associate, and sales associate; removes continuing education requirements for licensure renewal due to inactive status; revises provisions pertaining to board to transfer powers, duties, and responsibilities of board to DBPR; granting certain authority to department, rather than Florida Real Estate Appraisal Board; requires department to adopt rules; revises violations for which retail tobacco products dealers are penalized; revises retail nicotine product dealer administrative penalties; requires FDLE to accept and process certain fingerprints; specifies procedures for submitting and processing fingerprinting; requires department to conduct certain background checks."}], "other_titles": [], "other_identifiers": [], "actions": [{"description": "Filed", "date": "2025-12-02", "organization_id": "~{\"classification\": \"lower\"}", "classification": ["filing"], "related_entities": []}, {"description": "Referred to Industries & Professional Activities Subcommittee", "date": "2025-12-03", "organization_id": "~{\"classification\": \"lower\"}", "classification": ["referral-committee"], "related_entities": []}, {"description": "Referred to State Administration Budget Subcommittee", "date": "2025-12-03", "organization_id": "~{\"classification\": \"lower\"}", "classification": ["referral-committee"], "related_entities": []}, {"description": "Referred to Commerce Committee", "date": "2025-12-03", "organization_id": "~{\"classification\": \"lower\"}", "classification": ["referral-committee"], "related_entities": []}, {"description": "Now in Industries & Professional Activities Subcommittee", "date": "2025-12-03", "organization_id": "~{\"classification\": \"lower\"}", "classification": [], "related_entities": []}, {"description": "Added to Industries & Professional Activities Subcommittee agenda", "date": "2025-12-04", "organization_id": "~{\"classification\": \"lower\"}", "classification": [], "related_entities": []}, {"description": "Favorable with CS by Industries & Professional Activities Subcommittee", "date": "2025-12-11", "organization_id": "~{\"classification\": \"lower\"}", "classification": ["committee-passage-favorable"], "related_entities": []}, {"description": "Reported out of Industries & Professional Activities Subcommittee", "date": "2025-12-15", "organization_id": "~{\"classification\": \"lower\"}", "classification": [], "related_entities": []}, {"description": "Laid on Table under Rule 7.18(a)", "date": "2025-12-15", "organization_id": "~{\"classification\": \"lower\"}", "classification": ["deferral"], "related_entities": []}, {"description": "CS Filed", "date": "2025-12-15", "organization_id": "~{\"classification\": \"lower\"}", "classification": ["filing"], "related_entities": []}, {"description": "Referred to State Administration Budget Subcommittee", "date": "2025-12-18", "organization_id": "~{\"classification\": \"lower\"}", "classification": ["referral-committee"], "related_entities": []}, {"description": "Referred to Commerce Committee", "date": "2025-12-18", "organization_id": "~{\"classification\": \"lower\"}", "classification": ["referral-committee"], "related_entities": []}, {"description": "Now in State Administration Budget Subcommittee", "date": "2025-12-18", "organization_id": "~{\"classification\": \"lower\"}", "classification": [], "related_entities": []}], "sponsorships": [{"name": "Industries & Professional Activities Subcommittee", "classification": "primary", "entity_type": "organization", "primary": true, "person_id": null, "organization_id": "~{\"name\": \"Industries & Professional Activities Subcommittee\"}"}, {"name": "Yarkosky", "classification": "primary", "entity_type": "person", "primary": true, "person_id": "~{\"name\": \"Yarkosky\"}", "organization_id": null}], "related_bills": [], "versions": [{"note": "H 607 Filed", "links": [{"url": "https://flsenate.gov/Session/Bill/2026/607/BillText/Filed/PDF", "media_type": "application/pdf"}], "date": "", "classification": ""}, {"note": "H 607 c1", "links": [{"url": "https://flsenate.gov/Session/Bill/2026/607/BillText/c1/PDF", "media_type": "application/pdf"}], "date": "", "classification": ""}], "documents": [{"note": "Bill Analysis -- Industries & Professional Activities Subcommittee (Post-Meeting) (12/15/2025 1:48 PM)", "links": [{"url": "https://flsenate.gov/Session/Bill/2026/607/Analyses/h0607a.IPA.PDF", "media_type": "application/pdf"}], "date": "", "classification": ""}, {"note": "468807 - Amendment to H 607 Filed", "links": [{"url": "https://flsenate.gov/Session/Bill/2026/607/Amendment/468807/PDF", "media_type": "application/pdf"}], "date": "", "classification": ""}], "citations": [{"publication": "Florida Statues", "citation": "20.165", "citation_type": "proposed", "effective": null, "expires": null, "url": "https://flsenate.gov/laws/statutes/2025/20.165"}, {"publication": "Florida Statues", "citation": "120.54", "citation_type": "proposed", "effective": null, "expires": null, "url": "https://flsenate.gov/laws/statutes/2025/120.54"}, {"publication": "Florida Statues", "citation": "212.08", "citation_type": "proposed", "effective": null, "expires": null, "url": "https://flsenate.gov/laws/statutes/2025/212.08"}, {"publication": "Florida Statues", "citation": "215.5586", "citation_type": "proposed", "effective": null, "expires": null, "url": "https://flsenate.gov/laws/statutes/2025/215.5586"}, {"publication": "Florida Statues", "citation": "215.55871", "citation_type": "proposed", "effective": null, "expires": null, "url": "https://flsenate.gov/laws/statutes/2025/215.55871"}, {"publication": "Florida Statues", "citation": "259.1053", "citation_type": "proposed", "effective": null, "expires": null, "url": "https://flsenate.gov/laws/statutes/2025/259.1053"}, {"publication": "Florida Statues", "citation": "309.01", "citation_type": "proposed", "effective": null, "expires": null, "url": "https://flsenate.gov/laws/statutes/2025/309.01"}, {"publication": "Florida Statues", "citation": "310.0015", "citation_type": "proposed", "effective": null, "expires": null, "url": "https://flsenate.gov/laws/statutes/2025/310.0015"}, {"publication": "Florida Statues", "citation": "310.002", "citation_type": "proposed", "effective": null, "expires": null, "url": "https://flsenate.gov/laws/statutes/2025/310.002"}, {"publication": "Florida Statues", "citation": "310.011", "citation_type": "proposed", "effective": null, "expires": null, "url": "https://flsenate.gov/laws/statutes/2025/310.011"}, {"publication": "Florida Statues", "citation": "310.032", "citation_type": "proposed", "effective": null, "expires": null, "url": "https://flsenate.gov/laws/statutes/2025/310.032"}, {"publication": "Florida Statues", "citation": "310.042", "citation_type": "proposed", "effective": null, "expires": null, "url": "https://flsenate.gov/laws/statutes/2025/310.042"}, {"publication": "Florida Statues", "citation": "310.051", "citation_type": "proposed", "effective": null, "expires": null, "url": "https://flsenate.gov/laws/statutes/2025/310.051"}, {"publication": "Florida Statues", "citation": "310.061", "citation_type": "proposed", "effective": null, "expires": null, "url": "https://flsenate.gov/laws/statutes/2025/310.061"}, {"publication": "Florida Statues", "citation": "310.071", "citation_type": "proposed", "effective": null, "expires": null, "url": "https://flsenate.gov/laws/statutes/2025/310.071"}, {"publication": "Florida Statues", "citation": "310.073", "citation_type": "proposed", "effective": null, "expires": null, "url": "https://flsenate.gov/laws/statutes/2025/310.073"}, {"publication": "Florida Statues", "citation": "310.075", "citation_type": "proposed", "effective": null, "expires": null, "url": "https://flsenate.gov/laws/statutes/2025/310.075"}, {"publication": "Florida Statues", "citation": "310.081", "citation_type": "proposed", "effective": null, "expires": null, "url": "https://flsenate.gov/laws/statutes/2025/310.081"}, {"publication": "Florida Statues", "citation": "310.101", "citation_type": "proposed", "effective": null, "expires": null, "url": "https://flsenate.gov/laws/statutes/2025/310.101"}, {"publication": "Florida Statues", "citation": "310.102", "citation_type": "proposed", "effective": null, "expires": null, "url": "https://flsenate.gov/laws/statutes/2025/310.102"}, {"publication": "Florida Statues", "citation": "310.111", "citation_type": "proposed", "effective": null, "expires": null, "url": "https://flsenate.gov/laws/statutes/2025/310.111"}, {"publication": "Florida Statues", "citation": "310.121", "citation_type": "proposed", "effective": null, "expires": null, "url": "https://flsenate.gov/laws/statutes/2025/310.121"}, {"publication": "Florida Statues", "citation": "310.131", "citation_type": "proposed", "effective": null, "expires": null, "url": "https://flsenate.gov/laws/statutes/2025/310.131"}, {"publication": "Florida Statues", "citation": "310.142", "citation_type": "proposed", "effective": null, "expires": null, "url": "https://flsenate.gov/laws/statutes/2025/310.142"}, {"publication": "Florida Statues", "citation": "310.151", "citation_type": "proposed", "effective": null, "expires": null, "url": "https://flsenate.gov/laws/statutes/2025/310.151"}, {"publication": "Florida Statues", "citation": "310.183", "citation_type": "proposed", "effective": null, "expires": null, "url": "https://flsenate.gov/laws/statutes/2025/310.183"}, {"publication": "Florida Statues", "citation": "310.185", "citation_type": "proposed", "effective": null, "expires": null, "url": "https://flsenate.gov/laws/statutes/2025/310.185"}, {"publication": "Florida Statues", "citation": "326.002", "citation_type": "proposed", "effective": null, "expires": null, "url": "https://flsenate.gov/laws/statutes/2025/326.002"}, {"publication": "Florida Statues", "citation": "326.006", "citation_type": "proposed", "effective": null, "expires": null, "url": "https://flsenate.gov/laws/statutes/2025/326.006"}, {"publication": "Florida Statues", "citation": "376.303", "citation_type": "proposed", "effective": null, "expires": null, "url": "https://flsenate.gov/laws/statutes/2025/376.303"}, {"publication": "Florida Statues", "citation": "381.0065", "citation_type": "proposed", "effective": null, "expires": null, "url": "https://flsenate.gov/laws/statutes/2025/381.0065"}, {"publication": "Florida Statues", "citation": "399.035", "citation_type": "proposed", "effective": null, "expires": null, "url": "https://flsenate.gov/laws/statutes/2025/399.035"}, {"publication": "Florida Statues", "citation": "403.868", "citation_type": "proposed", "effective": null, "expires": null, "url": "https://flsenate.gov/laws/statutes/2025/403.868"}, {"publication": "Florida Statues", "citation": "403.9329", "citation_type": "proposed", "effective": null, "expires": null, "url": "https://flsenate.gov/laws/statutes/2025/403.9329"}, {"publication": "Florida Statues", "citation": "440.02", "citation_type": "proposed", "effective": null, "expires": null, "url": "https://flsenate.gov/laws/statutes/2025/440.02"}, {"publication": "Florida Statues", "citation": "448.26", "citation_type": "proposed", "effective": null, "expires": null, "url": "https://flsenate.gov/laws/statutes/2025/448.26"}, {"publication": "Florida Statues", "citation": "455.02", "citation_type": "proposed", "effective": null, "expires": null, "url": "https://flsenate.gov/laws/statutes/2025/455.02"}, {"publication": "Florida Statues", "citation": "455.203", "citation_type": "proposed", "effective": null, "expires": null, "url": "https://flsenate.gov/laws/statutes/2025/455.203"}, {"publication": "Florida Statues", "citation": "455.2124", "citation_type": "proposed", "effective": null, "expires": null, "url": "https://flsenate.gov/laws/statutes/2025/455.2124"}, {"publication": "Florida Statues", "citation": "455.2228", "citation_type": "proposed", "effective": null, "expires": null, "url": "https://flsenate.gov/laws/statutes/2025/455.2228"}, {"publication": "Florida Statues", "citation": "455.271", "citation_type": "proposed", "effective": null, "expires": null, "url": "https://flsenate.gov/laws/statutes/2025/455.271"}, {"publication": "Florida Statues", "citation": "468.382", "citation_type": "proposed", "effective": null, "expires": null, "url": "https://flsenate.gov/laws/statutes/2025/468.382"}, {"publication": "Florida Statues", "citation": "468.384", "citation_type": "proposed", "effective": null, "expires": null, "url": "https://flsenate.gov/laws/statutes/2025/468.384"}, {"publication": "Florida Statues", "citation": "468.385", "citation_type": "proposed", "effective": null, "expires": null, "url": "https://flsenate.gov/laws/statutes/2025/468.385"}, {"publication": "Florida Statues", "citation": "468.3851", "citation_type": "proposed", "effective": null, "expires": null, "url": "https://flsenate.gov/laws/statutes/2025/468.3851"}, {"publication": "Florida Statues", "citation": "468.3852", "citation_type": "proposed", "effective": null, "expires": null, "url": "https://flsenate.gov/laws/statutes/2025/468.3852"}, {"publication": "Florida Statues", "citation": "468.3855", "citation_type": "proposed", "effective": null, "expires": null, "url": "https://flsenate.gov/laws/statutes/2025/468.3855"}, {"publication": "Florida Statues", "citation": "468.386", "citation_type": "proposed", "effective": null, "expires": null, "url": "https://flsenate.gov/laws/statutes/2025/468.386"}, {"publication": "Florida Statues", "citation": "468.387", "citation_type": "proposed", "effective": null, "expires": null, "url": "https://flsenate.gov/laws/statutes/2025/468.387"}, {"publication": "Florida Statues", "citation": "468.388", "citation_type": "proposed", "effective": null, "expires": null, "url": "https://flsenate.gov/laws/statutes/2025/468.388"}, {"publication": "Florida Statues", "citation": "468.389", "citation_type": "proposed", "effective": null, "expires": null, "url": "https://flsenate.gov/laws/statutes/2025/468.389"}, {"publication": "Florida Statues", "citation": "468.392", "citation_type": "proposed", "effective": null, "expires": null, "url": "https://flsenate.gov/laws/statutes/2025/468.392"}, {"publication": "Florida Statues", "citation": "468.393", "citation_type": "proposed", "effective": null, "expires": null, "url": "https://flsenate.gov/laws/statutes/2025/468.393"}, {"publication": "Florida Statues", "citation": "468.395", "citation_type": "proposed", "effective": null, "expires": null, "url": "https://flsenate.gov/laws/statutes/2025/468.395"}, {"publication": "Florida Statues", "citation": "468.396", "citation_type": "proposed", "effective": null, "expires": null, "url": "https://flsenate.gov/laws/statutes/2025/468.396"}, {"publication": "Florida Statues", "citation": "468.397", "citation_type": "proposed", "effective": null, "expires": null, "url": "https://flsenate.gov/laws/statutes/2025/468.397"}, {"publication": "Florida Statues", "citation": "468.398", "citation_type": "proposed", "effective": null, "expires": null, "url": "https://flsenate.gov/laws/statutes/2025/468.398"}, {"publication": "Florida Statues", "citation": "468.399", "citation_type": "proposed", "effective": null, "expires": null, "url": "https://flsenate.gov/laws/statutes/2025/468.399"}, {"publication": "Florida Statues", "citation": "468.404", "citation_type": "proposed", "effective": null, "expires": null, "url": "https://flsenate.gov/laws/statutes/2025/468.404"}, {"publication": "Florida Statues", "citation": "468.407", "citation_type": "proposed", "effective": null, "expires": null, "url": "https://flsenate.gov/laws/statutes/2025/468.407"}, {"publication": "Florida Statues", "citation": "468.431", "citation_type": "proposed", "effective": null, "expires": null, "url": "https://flsenate.gov/laws/statutes/2025/468.431"}, {"publication": "Florida Statues", "citation": "468.4315", "citation_type": "proposed", "effective": null, "expires": null, "url": "https://flsenate.gov/laws/statutes/2025/468.4315"}, {"publication": "Florida Statues", "citation": "468.433", "citation_type": "proposed", "effective": null, "expires": null, "url": "https://flsenate.gov/laws/statutes/2025/468.433"}, {"publication": "Florida Statues", "citation": "468.4336", "citation_type": "proposed", "effective": null, "expires": null, "url": "https://flsenate.gov/laws/statutes/2025/468.4336"}, {"publication": "Florida Statues", "citation": "468.4337", "citation_type": "proposed", "effective": null, "expires": null, "url": "https://flsenate.gov/laws/statutes/2025/468.4337"}, {"publication": "Florida Statues", "citation": "468.4338", "citation_type": "proposed", "effective": null, "expires": null, "url": "https://flsenate.gov/laws/statutes/2025/468.4338"}, {"publication": "Florida Statues", "citation": "468.435", "citation_type": "proposed", "effective": null, "expires": null, "url": "https://flsenate.gov/laws/statutes/2025/468.435"}, {"publication": "Florida Statues", "citation": "468.436", "citation_type": "proposed", "effective": null, "expires": null, "url": "https://flsenate.gov/laws/statutes/2025/468.436"}, {"publication": "Florida Statues", "citation": "468.520", "citation_type": "proposed", "effective": null, "expires": null, "url": "https://flsenate.gov/laws/statutes/2025/468.520"}, {"publication": "Florida Statues", "citation": "468.521", "citation_type": "proposed", "effective": null, "expires": null, "url": "https://flsenate.gov/laws/statutes/2025/468.521"}, {"publication": "Florida Statues", "citation": "468.522", "citation_type": "proposed", "effective": null, "expires": null, "url": "https://flsenate.gov/laws/statutes/2025/468.522"}, {"publication": "Florida Statues", "citation": "468.523", "citation_type": "proposed", "effective": null, "expires": null, "url": "https://flsenate.gov/laws/statutes/2025/468.523"}, {"publication": "Florida Statues", "citation": "468.524", "citation_type": "proposed", "effective": null, "expires": null, "url": "https://flsenate.gov/laws/statutes/2025/468.524"}, {"publication": "Florida Statues", "citation": "468.5245", "citation_type": "proposed", "effective": null, "expires": null, "url": "https://flsenate.gov/laws/statutes/2025/468.5245"}, {"publication": "Florida Statues", "citation": "468.525", "citation_type": "proposed", "effective": null, "expires": null, "url": "https://flsenate.gov/laws/statutes/2025/468.525"}, {"publication": "Florida Statues", "citation": "468.526", "citation_type": "proposed", "effective": null, "expires": null, "url": "https://flsenate.gov/laws/statutes/2025/468.526"}, {"publication": "Florida Statues", "citation": "468.527", "citation_type": "proposed", "effective": null, "expires": null, "url": "https://flsenate.gov/laws/statutes/2025/468.527"}, {"publication": "Florida Statues", "citation": "468.5275", "citation_type": "proposed", "effective": null, "expires": null, "url": "https://flsenate.gov/laws/statutes/2025/468.5275"}, {"publication": "Florida Statues", "citation": "468.529", "citation_type": "proposed", "effective": null, "expires": null, "url": "https://flsenate.gov/laws/statutes/2025/468.529"}, {"publication": "Florida Statues", "citation": "468.530", "citation_type": "proposed", "effective": null, "expires": null, "url": "https://flsenate.gov/laws/statutes/2025/468.530"}, {"publication": "Florida Statues", "citation": "468.531", "citation_type": "proposed", "effective": null, "expires": null, "url": "https://flsenate.gov/laws/statutes/2025/468.531"}, {"publication": "Florida Statues", "citation": "468.532", "citation_type": "proposed", "effective": null, "expires": null, "url": "https://flsenate.gov/laws/statutes/2025/468.532"}, {"publication": "Florida Statues", "citation": "468.603", "citation_type": "proposed", "effective": null, "expires": null, "url": "https://flsenate.gov/laws/statutes/2025/468.603"}, {"publication": "Florida Statues", "citation": "468.605", "citation_type": "proposed", "effective": null, "expires": null, "url": "https://flsenate.gov/laws/statutes/2025/468.605"}, {"publication": "Florida Statues", "citation": "468.606", "citation_type": "proposed", "effective": null, "expires": null, "url": "https://flsenate.gov/laws/statutes/2025/468.606"}, {"publication": "Florida Statues", "citation": "468.607", "citation_type": "proposed", "effective": null, "expires": null, "url": "https://flsenate.gov/laws/statutes/2025/468.607"}, {"publication": "Florida Statues", "citation": "468.609", "citation_type": "proposed", "effective": null, "expires": null, "url": "https://flsenate.gov/laws/statutes/2025/468.609"}, {"publication": "Florida Statues", "citation": "468.613", "citation_type": "proposed", "effective": null, "expires": null, "url": "https://flsenate.gov/laws/statutes/2025/468.613"}, {"publication": "Florida Statues", "citation": "468.619", "citation_type": "proposed", "effective": null, "expires": null, "url": "https://flsenate.gov/laws/statutes/2025/468.619"}, {"publication": "Florida Statues", "citation": "468.621", "citation_type": "proposed", "effective": null, "expires": null, "url": "https://flsenate.gov/laws/statutes/2025/468.621"}, {"publication": "Florida Statues", "citation": "468.627", "citation_type": "proposed", "effective": null, "expires": null, "url": "https://flsenate.gov/laws/statutes/2025/468.627"}, {"publication": "Florida Statues", "citation": "468.629", "citation_type": "proposed", "effective": null, "expires": null, "url": "https://flsenate.gov/laws/statutes/2025/468.629"}, {"publication": "Florida Statues", "citation": "468.631", "citation_type": "proposed", "effective": null, "expires": null, "url": "https://flsenate.gov/laws/statutes/2025/468.631"}, {"publication": "Florida Statues", "citation": "468.8312", "citation_type": "proposed", "effective": null, "expires": null, "url": "https://flsenate.gov/laws/statutes/2025/468.8312"}, {"publication": "Florida Statues", "citation": "468.8315", "citation_type": "proposed", "effective": null, "expires": null, "url": "https://flsenate.gov/laws/statutes/2025/468.8315"}, {"publication": "Florida Statues", "citation": "468.8316", "citation_type": "proposed", "effective": null, "expires": null, "url": "https://flsenate.gov/laws/statutes/2025/468.8316"}, {"publication": "Florida Statues", "citation": "468.8412", "citation_type": "proposed", "effective": null, "expires": null, "url": "https://flsenate.gov/laws/statutes/2025/468.8412"}, {"publication": "Florida Statues", "citation": "468.8415", "citation_type": "proposed", "effective": null, "expires": null, "url": "https://flsenate.gov/laws/statutes/2025/468.8415"}, {"publication": "Florida Statues", "citation": "468.8416", "citation_type": "proposed", "effective": null, "expires": null, "url": "https://flsenate.gov/laws/statutes/2025/468.8416"}, {"publication": "Florida Statues", "citation": "468.8417", "citation_type": "proposed", "effective": null, "expires": null, "url": "https://flsenate.gov/laws/statutes/2025/468.8417"}, {"publication": "Florida Statues", "citation": "468.8419", "citation_type": "proposed", "effective": null, "expires": null, "url": "https://flsenate.gov/laws/statutes/2025/468.8419"}, {"publication": "Florida Statues", "citation": "469.004", "citation_type": "proposed", "effective": null, "expires": null, "url": "https://flsenate.gov/laws/statutes/2025/469.004"}, {"publication": "Florida Statues", "citation": "469.012", "citation_type": "proposed", "effective": null, "expires": null, "url": "https://flsenate.gov/laws/statutes/2025/469.012"}, {"publication": "Florida Statues", "citation": "469.013", "citation_type": "proposed", "effective": null, "expires": null, "url": "https://flsenate.gov/laws/statutes/2025/469.013"}, {"publication": "Florida Statues", "citation": "471.007", "citation_type": "proposed", "effective": null, "expires": null, "url": "https://flsenate.gov/laws/statutes/2025/471.007"}, {"publication": "Florida Statues", "citation": "471.011", "citation_type": "proposed", "effective": null, "expires": null, "url": "https://flsenate.gov/laws/statutes/2025/471.011"}, {"publication": "Florida Statues", "citation": "471.015", "citation_type": "proposed", "effective": null, "expires": null, "url": "https://flsenate.gov/laws/statutes/2025/471.015"}, {"publication": "Florida Statues", "citation": "471.017", "citation_type": "proposed", "effective": null, "expires": null, "url": "https://flsenate.gov/laws/statutes/2025/471.017"}, {"publication": "Florida Statues", "citation": "471.019", "citation_type": "proposed", "effective": null, "expires": null, "url": "https://flsenate.gov/laws/statutes/2025/471.019"}, {"publication": "Florida Statues", "citation": "471.0195", "citation_type": "proposed", "effective": null, "expires": null, "url": "https://flsenate.gov/laws/statutes/2025/471.0195"}, {"publication": "Florida Statues", "citation": "471.045", "citation_type": "proposed", "effective": null, "expires": null, "url": "https://flsenate.gov/laws/statutes/2025/471.045"}, {"publication": "Florida Statues", "citation": "472.003", "citation_type": "proposed", "effective": null, "expires": null, "url": "https://flsenate.gov/laws/statutes/2025/472.003"}, {"publication": "Florida Statues", "citation": "472.005", "citation_type": "proposed", "effective": null, "expires": null, "url": "https://flsenate.gov/laws/statutes/2025/472.005"}, {"publication": "Florida Statues", "citation": "472.006", "citation_type": "proposed", "effective": null, "expires": null, "url": "https://flsenate.gov/laws/statutes/2025/472.006"}, {"publication": "Florida Statues", "citation": "472.007", "citation_type": "proposed", "effective": null, "expires": null, "url": "https://flsenate.gov/laws/statutes/2025/472.007"}, {"publication": "Florida Statues", "citation": "472.008", "citation_type": "proposed", "effective": null, "expires": null, "url": "https://flsenate.gov/laws/statutes/2025/472.008"}, {"publication": "Florida Statues", "citation": "472.009", "citation_type": "proposed", "effective": null, "expires": null, "url": "https://flsenate.gov/laws/statutes/2025/472.009"}, {"publication": "Florida Statues", "citation": "472.011", "citation_type": "proposed", "effective": null, "expires": null, "url": "https://flsenate.gov/laws/statutes/2025/472.011"}, {"publication": "Florida Statues", "citation": "472.017", "citation_type": "proposed", "effective": null, "expires": null, "url": "https://flsenate.gov/laws/statutes/2025/472.017"}, {"publication": "Florida Statues", "citation": "472.018", "citation_type": "proposed", "effective": null, "expires": null, "url": "https://flsenate.gov/laws/statutes/2025/472.018"}, {"publication": "Florida Statues", "citation": "472.019", "citation_type": "proposed", "effective": null, "expires": null, "url": "https://flsenate.gov/laws/statutes/2025/472.019"}, {"publication": "Florida Statues", "citation": "472.0202", "citation_type": "proposed", "effective": null, "expires": null, "url": "https://flsenate.gov/laws/statutes/2025/472.0202"}, {"publication": "Florida Statues", "citation": "472.0203", "citation_type": "proposed", "effective": null, "expires": null, "url": "https://flsenate.gov/laws/statutes/2025/472.0203"}, {"publication": "Florida Statues", "citation": "473.302", "citation_type": "proposed", "effective": null, "expires": null, "url": "https://flsenate.gov/laws/statutes/2025/473.302"}, {"publication": "Florida Statues", "citation": "473.303", "citation_type": "proposed", "effective": null, "expires": null, "url": "https://flsenate.gov/laws/statutes/2025/473.303"}, {"publication": "Florida Statues", "citation": "473.3035", "citation_type": "proposed", "effective": null, "expires": null, "url": "https://flsenate.gov/laws/statutes/2025/473.3035"}, {"publication": "Florida Statues", "citation": "473.304", "citation_type": "proposed", "effective": null, "expires": null, "url": "https://flsenate.gov/laws/statutes/2025/473.304"}, {"publication": "Florida Statues", "citation": "473.305", "citation_type": "proposed", "effective": null, "expires": null, "url": "https://flsenate.gov/laws/statutes/2025/473.305"}, {"publication": "Florida Statues", "citation": "473.306", "citation_type": "proposed", "effective": null, "expires": null, "url": "https://flsenate.gov/laws/statutes/2025/473.306"}, {"publication": "Florida Statues", "citation": "473.308", "citation_type": "proposed", "effective": null, "expires": null, "url": "https://flsenate.gov/laws/statutes/2025/473.308"}], "sources": [{"url": "https://flsenate.gov/Session/Bill/2026/607/ByCategory", "note": ""}], "extras": {}, "jurisdiction": {"id": "ocd-jurisdiction/country:us/state:fl/government", "name": "Florida", "classification": "state", "division_id": "ocd-division/country:us/state:fl"}, "scraped_at": "2025-12-23T11:56:16+00:00", "_id": "8954d77c-dff1-11f0-8808-56324ac6fe2a"}