{"legislative_session": "2026", "identifier": "SB 418", "title": "Law Enforcement Officer Interactions with Individuals with Autism Spectrum Disorder", "from_organization": "~{\"classification\": \"upper\"}", "classification": ["bill"], "subject": ["subject index"], "abstracts": [{"note": "summary", "abstract": "Law Enforcement Officer Interactions with Individuals with Autism Spectrum Disorder;  Requiring the Department of Highway Safety and Motor Vehicles to establish a program to improve communication between individuals with autism spectrum disorder and law enforcement officers under certain circumstances; requiring the department to develop and make available to individuals with autism spectrum disorder a certain envelope by a specified date; defining the terms \u201cagency\u201d and \u201cautism spectrum disorder\u201d; requiring the Criminal Justice Standards and Training Commission within the Department of Law Enforcement to establish an employment training component relating to individuals with autism spectrum disorder, etc."}], "other_titles": [], "other_identifiers": [], "actions": [{"description": "Filed", "date": "2025-11-06", "organization_id": "~{\"classification\": \"upper\"}", "classification": ["filing"], "related_entities": []}, {"description": "Referred to Criminal Justice; Appropriations Committee on Criminal and Civil Justice; Fiscal Policy", "date": "2025-11-17", "organization_id": "~{\"classification\": \"upper\"}", "classification": ["referral-committee"], "related_entities": []}, {"description": "Introduced", "date": "2026-01-13", "organization_id": "~{\"classification\": \"upper\"}", "classification": ["introduction"], "related_entities": []}, {"description": "On Committee agenda-- Criminal Justice, 01/26/26, 3:30 pm, 37 Senate Building", "date": "2026-01-21", "organization_id": "~{\"classification\": \"upper\"}", "classification": [], "related_entities": []}, {"description": "Favorable by Criminal Justice; YEAS 8 NAYS 0", "date": "2026-01-26", "organization_id": "~{\"classification\": \"upper\"}", "classification": ["committee-passage-favorable"], "related_entities": []}, {"description": "Now in Appropriations Committee on Criminal and Civil Justice", "date": "2026-01-27", "organization_id": "~{\"classification\": \"upper\"}", "classification": [], "related_entities": []}, {"description": "On Committee agenda-- Appropriations Committee on Criminal and Civil Justice, 02/04/26, 3:45 pm, 37 Senate Building", "date": "2026-01-30", "organization_id": "~{\"classification\": \"upper\"}", "classification": [], "related_entities": []}, {"description": "Favorable by Appropriations Committee on Criminal and Civil Justice; YEAS 8 NAYS 0", "date": "2026-02-04", "organization_id": "~{\"classification\": \"upper\"}", "classification": ["committee-passage-favorable"], "related_entities": []}, {"description": "Now in Fiscal Policy", "date": "2026-02-04", "organization_id": "~{\"classification\": \"upper\"}", "classification": [], "related_entities": []}, {"description": "On Committee agenda-- Fiscal Policy, 02/12/26, 9:00 am, 110 Senate Building", "date": "2026-02-09", "organization_id": "~{\"classification\": \"upper\"}", "classification": [], "related_entities": []}, {"description": "Favorable by- Fiscal Policy; YEAS 19 NAYS 0", "date": "2026-02-12", "organization_id": "~{\"classification\": \"upper\"}", "classification": ["committee-passage-favorable"], "related_entities": []}, {"description": "Placed on Calendar, on 2nd reading", "date": "2026-02-12", "organization_id": "~{\"classification\": \"upper\"}", "classification": [], "related_entities": []}, {"description": "Placed on Special Order Calendar, 02/19/26", "date": "2026-02-17", "organization_id": "~{\"classification\": \"upper\"}", "classification": [], "related_entities": []}, {"description": "Read 2nd time", "date": "2026-02-19", "organization_id": "~{\"classification\": \"upper\"}", "classification": ["reading-2"], "related_entities": []}, {"description": "Read 3rd time", "date": "2026-02-19", "organization_id": "~{\"classification\": \"upper\"}", "classification": ["reading-3"], "related_entities": []}, {"description": "Passed; YEAS 38 NAYS 0", "date": "2026-02-19", "organization_id": "~{\"classification\": \"upper\"}", "classification": ["passage"], "related_entities": []}, {"description": "Immediately certified", "date": "2026-02-19", "organization_id": "~{\"classification\": \"upper\"}", "classification": [], "related_entities": []}, {"description": "In Messages", "date": "2026-02-19", "organization_id": "~{\"classification\": \"lower\"}", "classification": [], "related_entities": []}], "sponsorships": [{"name": "Jones", "classification": "primary", "entity_type": "person", "primary": true, "person_id": "~{\"name\": \"Jones\"}", "organization_id": null}, {"name": "Smith", "classification": "cosponsor", "entity_type": "person", "primary": false, "person_id": "~{\"name\": \"Smith\"}", "organization_id": null}], "related_bills": [], "versions": [{"note": "S 418 Filed", "links": [{"url": "https://flsenate.gov/Session/Bill/2026/418/BillText/Filed/HTML", "media_type": "text/html"}, {"url": "https://flsenate.gov/Session/Bill/2026/418/BillText/Filed/PDF", "media_type": "application/pdf"}], "date": "", "classification": ""}], "documents": [{"note": "Bill Analysis -- Criminal Justice (Pre-Meeting) (1/23/2026 3:16 PM)", "links": [{"url": "https://flsenate.gov/Session/Bill/2026/418/Analyses/2026s00418.pre.cj.PDF", "media_type": "application/pdf"}], "date": "", "classification": ""}, {"note": "Bill Analysis -- Criminal Justice (Post-Meeting) (1/26/2026 6:38 PM)", "links": [{"url": "https://flsenate.gov/Session/Bill/2026/418/Analyses/2026s00418.cj.PDF", "media_type": "application/pdf"}], "date": "", "classification": ""}, {"note": "Bill Analysis -- Appropriations Committee on Criminal and Civil Justice (Pre-Meeting) (2/3/2026 9:41 AM)", "links": [{"url": "https://flsenate.gov/Session/Bill/2026/418/Analyses/2026s00418.pre.acj.PDF", "media_type": "application/pdf"}], "date": "", "classification": ""}, {"note": "Bill Analysis -- Appropriations Committee on Criminal and Civil Justice (Post-Meeting) (2/4/2026 5:14 PM)", "links": [{"url": "https://flsenate.gov/Session/Bill/2026/418/Analyses/2026s00418.acj.PDF", "media_type": "application/pdf"}], "date": "", "classification": ""}, {"note": "Bill Analysis -- Fiscal Policy (Pre-Meeting) (2/11/2026 8:34 AM)", "links": [{"url": "https://flsenate.gov/Session/Bill/2026/418/Analyses/2026s00418.pre.fp.PDF", "media_type": "application/pdf"}], "date": "", "classification": ""}, {"note": "Bill Analysis -- Fiscal Policy (Post-Meeting) (2/12/2026 1:26 PM)", "links": [{"url": "https://flsenate.gov/Session/Bill/2026/418/Analyses/2026s00418.fp.PDF", "media_type": "application/pdf"}], "date": "", "classification": ""}], "citations": [], "sources": [{"url": "https://flsenate.gov/Session/Bill/2026/418/ByCategory", "note": ""}], "extras": {}, "jurisdiction": {"id": "ocd-jurisdiction/country:us/state:fl/government", "name": "Florida", "classification": "state", "division_id": "ocd-division/country:us/state:fl"}, "scraped_at": "2026-02-24T13:50:44+00:00", "_id": "02693cf2-1166-11f1-984f-22865c4544ef"}