{"legislative_session": "2026", "identifier": "HB 721", "title": "Foreign Students Enrolled in Public Postsecondary Educational Institutions", "from_organization": "~{\"classification\": \"lower\"}", "classification": ["bill"], "subject": ["k"], "abstracts": [{"note": "summary", "abstract": "Foreign Students Enrolled in Public Postsecondary Educational Institutions;  Requires FCS institutions & state universities to limit number of enrolled students who are citizens of foreign country & who are not permanent residents of United States to specified percentage of students enrolled at institution or university."}], "other_titles": [], "other_identifiers": [], "actions": [{"description": "Filed", "date": "2025-12-10", "organization_id": "~{\"classification\": \"lower\"}", "classification": ["filing"], "related_entities": []}, {"description": "Referred to Careers & Workforce Subcommittee", "date": "2025-12-16", "organization_id": "~{\"classification\": \"lower\"}", "classification": ["referral-committee"], "related_entities": []}, {"description": "Referred to Education Administration Subcommittee", "date": "2025-12-16", "organization_id": "~{\"classification\": \"lower\"}", "classification": ["referral-committee"], "related_entities": []}, {"description": "Referred to Education & Employment Committee", "date": "2025-12-16", "organization_id": "~{\"classification\": \"lower\"}", "classification": ["referral-committee"], "related_entities": []}, {"description": "Now in Careers & Workforce Subcommittee", "date": "2025-12-16", "organization_id": "~{\"classification\": \"lower\"}", "classification": [], "related_entities": []}], "sponsorships": [{"name": "Jacques", "classification": "primary", "entity_type": "person", "primary": true, "person_id": "~{\"name\": \"Jacques\"}", "organization_id": null}], "related_bills": [], "versions": [{"note": "H 721 Filed", "links": [{"url": "https://flsenate.gov/Session/Bill/2026/721/BillText/Filed/PDF", "media_type": "application/pdf"}], "date": "", "classification": ""}], "documents": [], "citations": [], "sources": [{"url": "https://flsenate.gov/Session/Bill/2026/721/ByCategory", "note": ""}], "extras": {}, "jurisdiction": {"id": "ocd-jurisdiction/country:us/state:fl/government", "name": "Florida", "classification": "state", "division_id": "ocd-division/country:us/state:fl"}, "scraped_at": "2026-01-08T12:32:24+00:00", "_id": "bc76c8ea-ec85-11f0-b558-76a7e43656f7"}