{"legislative_session": "2026", "identifier": "HB 1219", "title": "Waterbody Designations", "from_organization": "~{\"classification\": \"lower\"}", "classification": ["bill"], "subject": ["public lands and property"], "abstracts": [{"note": "summary", "abstract": "Waterbody Designations;  Designates Andrew \"Red\" Harris Spoil Island; directs DEP to erect suitable markers."}], "other_titles": [], "other_identifiers": [], "actions": [{"description": "Filed", "date": "2026-01-08", "organization_id": "~{\"classification\": \"lower\"}", "classification": ["filing"], "related_entities": []}, {"description": "1st Reading (Original Filed Version)", "date": "2026-01-13", "organization_id": "~{\"classification\": \"lower\"}", "classification": ["filing", "reading-1"], "related_entities": []}, {"description": "Referred to Natural Resources & Disasters Subcommittee", "date": "2026-01-15", "organization_id": "~{\"classification\": \"lower\"}", "classification": ["referral-committee"], "related_entities": []}, {"description": "Referred to State Affairs Committee", "date": "2026-01-15", "organization_id": "~{\"classification\": \"lower\"}", "classification": ["referral-committee"], "related_entities": []}, {"description": "Now in Natural Resources & Disasters Subcommittee", "date": "2026-01-15", "organization_id": "~{\"classification\": \"lower\"}", "classification": [], "related_entities": []}, {"description": "Added to Natural Resources & Disasters Subcommittee agenda", "date": "2026-01-26", "organization_id": "~{\"classification\": \"lower\"}", "classification": [], "related_entities": []}, {"description": "Favorable with CS by Natural Resources & Disasters Subcommittee", "date": "2026-01-28", "organization_id": "~{\"classification\": \"lower\"}", "classification": ["committee-passage-favorable"], "related_entities": []}, {"description": "Reported out of Natural Resources & Disasters Subcommittee", "date": "2026-01-29", "organization_id": "~{\"classification\": \"lower\"}", "classification": [], "related_entities": []}, {"description": "Laid on Table under Rule 7.18(a)", "date": "2026-01-29", "organization_id": "~{\"classification\": \"lower\"}", "classification": ["deferral"], "related_entities": []}, {"description": "CS Filed", "date": "2026-01-29", "organization_id": "~{\"classification\": \"lower\"}", "classification": ["filing"], "related_entities": []}, {"description": "1st Reading (Committee Substitute 1)", "date": "2026-01-29", "organization_id": "~{\"classification\": \"lower\"}", "classification": ["reading-1"], "related_entities": []}, {"description": "Referred to State Affairs Committee", "date": "2026-01-30", "organization_id": "~{\"classification\": \"lower\"}", "classification": ["referral-committee"], "related_entities": []}, {"description": "Now in State Affairs Committee", "date": "2026-01-30", "organization_id": "~{\"classification\": \"lower\"}", "classification": [], "related_entities": []}, {"description": "Added to State Affairs Committee agenda", "date": "2026-02-06", "organization_id": "~{\"classification\": \"lower\"}", "classification": [], "related_entities": []}, {"description": "Favorable by State Affairs Committee", "date": "2026-02-10", "organization_id": "~{\"classification\": \"lower\"}", "classification": ["committee-passage-favorable"], "related_entities": []}, {"description": "Reported out of State Affairs Committee", "date": "2026-02-10", "organization_id": "~{\"classification\": \"lower\"}", "classification": [], "related_entities": []}, {"description": "Bill released to House Calendar", "date": "2026-02-10", "organization_id": "~{\"classification\": \"lower\"}", "classification": [], "related_entities": []}, {"description": "Added to Second Reading Calendar", "date": "2026-02-10", "organization_id": "~{\"classification\": \"lower\"}", "classification": [], "related_entities": []}, {"description": "Bill added to Special Order Calendar (2/25/2026)", "date": "2026-02-19", "organization_id": "~{\"classification\": \"lower\"}", "classification": [], "related_entities": []}, {"description": "Read 2nd time", "date": "2026-02-25", "organization_id": "~{\"classification\": \"lower\"}", "classification": ["reading-2"], "related_entities": []}, {"description": "Added to Third Reading Calendar", "date": "2026-02-25", "organization_id": "~{\"classification\": \"lower\"}", "classification": [], "related_entities": []}, {"description": "Read 3rd time", "date": "2026-02-25", "organization_id": "~{\"classification\": \"lower\"}", "classification": ["reading-3"], "related_entities": []}, {"description": "CS passed; YEAS 114, NAYS 0", "date": "2026-02-25", "organization_id": "~{\"classification\": \"lower\"}", "classification": ["passage"], "related_entities": []}, {"description": "In Messages", "date": "2026-02-25", "organization_id": "~{\"classification\": \"upper\"}", "classification": [], "related_entities": []}, {"description": "Referred to Rules", "date": "2026-02-26", "organization_id": "~{\"classification\": \"upper\"}", "classification": ["referral-committee"], "related_entities": []}, {"description": "Received", "date": "2026-02-26", "organization_id": "~{\"classification\": \"upper\"}", "classification": ["enrolled"], "related_entities": []}], "sponsorships": [{"name": "Natural Resources & Disasters Subcommittee", "classification": "primary", "entity_type": "organization", "primary": true, "person_id": null, "organization_id": "~{\"name\": \"Natural Resources & Disasters Subcommittee\"}"}, {"name": "Snyder", "classification": "primary", "entity_type": "person", "primary": true, "person_id": "~{\"name\": \"Snyder\"}", "organization_id": null}], "related_bills": [], "versions": [{"note": "H 1219 Filed", "links": [{"url": "https://flsenate.gov/Session/Bill/2026/1219/BillText/Filed/PDF", "media_type": "application/pdf"}], "date": "", "classification": ""}, {"note": "H 1219 c1", "links": [{"url": "https://flsenate.gov/Session/Bill/2026/1219/BillText/c1/PDF", "media_type": "application/pdf"}], "date": "", "classification": ""}], "documents": [{"note": "Bill Analysis -- Natural Resources & Disasters Subcommittee (Post-Meeting) (1/29/2026 5:42 PM)", "links": [{"url": "https://flsenate.gov/Session/Bill/2026/1219/Analyses/h1219a.NRD.PDF", "media_type": "application/pdf"}], "date": "", "classification": ""}, {"note": "Bill Analysis -- State Affairs Committee (Post-Meeting) (2/10/2026 2:18 PM)", "links": [{"url": "https://flsenate.gov/Session/Bill/2026/1219/Analyses/h1219c.SAC.PDF", "media_type": "application/pdf"}], "date": "", "classification": ""}, {"note": "150589 - Amendment to H 1219 Filed", "links": [{"url": "https://flsenate.gov/Session/Bill/2026/1219/Amendment/150589/PDF", "media_type": "application/pdf"}], "date": "", "classification": ""}], "citations": [], "sources": [{"url": "https://flsenate.gov/Session/Bill/2026/1219/ByCategory", "note": ""}], "extras": {}, "jurisdiction": {"id": "ocd-jurisdiction/country:us/state:fl/government", "name": "Florida", "classification": "state", "division_id": "ocd-division/country:us/state:fl"}, "scraped_at": "2026-03-01T14:15:30+00:00", "_id": "6bcc19e0-156b-11f1-9230-1af52c5ed1c3"}