{"legislative_session": "2026", "identifier": "HB 6023", "title": "Educational Facilities", "from_organization": "~{\"classification\": \"lower\"}", "classification": ["bill"], "subject": ["subject index"], "abstracts": [{"note": "summary", "abstract": "Educational Facilities;  Removes provision authorizing school of hope to colocate with another school in public school facility; removes provision requiring school district to permit school of hope to use underused, vacant, or surplus school district facility; removes requirement for students enrolled in school of hope to be included in school district's total capital outlay full-time equivalent membership; & removes provision authorizing hope operator establishing school of hope to use such facility at no cost."}], "other_titles": [], "other_identifiers": [], "actions": [{"description": "Filed", "date": "2026-01-06", "organization_id": "~{\"classification\": \"lower\"}", "classification": ["filing"], "related_entities": []}], "sponsorships": [{"name": "Gantt", "classification": "primary", "entity_type": "person", "primary": true, "person_id": "~{\"name\": \"Gantt\"}", "organization_id": null}, {"name": "Bartleman", "classification": "primary", "entity_type": "person", "primary": true, "person_id": "~{\"name\": \"Bartleman\"}", "organization_id": null}], "related_bills": [], "versions": [{"note": "H 6023 Filed", "links": [{"url": "https://flsenate.gov/Session/Bill/2026/6023/BillText/Filed/PDF", "media_type": "application/pdf"}], "date": "", "classification": ""}], "documents": [], "citations": [{"publication": "Florida Statues", "citation": "1002.333", "citation_type": "proposed", "effective": null, "expires": null, "url": "https://flsenate.gov/laws/statutes/2025/1002.333"}], "sources": [{"url": "https://flsenate.gov/Session/Bill/2026/6023/ByCategory", "note": ""}], "extras": {}, "jurisdiction": {"id": "ocd-jurisdiction/country:us/state:fl/government", "name": "Florida", "classification": "state", "division_id": "ocd-division/country:us/state:fl"}, "scraped_at": "2026-01-11T11:42:57+00:00", "_id": "10fca962-eee2-11f0-a6a9-c610f9824b45"}