{"legislative_session": "2026", "identifier": "SB 2516", "title": "Higher Education", "from_organization": "~{\"classification\": \"upper\"}", "classification": ["bill"], "subject": ["regulation of professions and occupations", "subject index"], "abstracts": [{"note": "summary", "abstract": "Higher Education;  Establishing the Florida Center for Nursing within the University of South Florida; providing that a specified fee waiver applies to a student\u2019s out-of-pocket expenses for tuition and fees after other aid is applied; providing that the LINE Fund was established for shortages in health science professions in addition to nursing; requiring institutions awarded grant funds to submit an annual report by a certain date to the center instead of the Board of Governors or the Department of Education; requiring the Office of Reimagining Education and Career Help to provide specified data to the department, etc."}], "other_titles": [], "other_identifiers": [], "actions": [{"description": "Submitted for consideration by Appropriations", "date": "2026-02-13", "organization_id": "~{\"classification\": \"upper\"}", "classification": [], "related_entities": []}, {"description": "On Committee agenda-- Appropriations, 02/18/26, 1:30 pm, 412 Knott Building", "date": "2026-02-13", "organization_id": "~{\"classification\": \"upper\"}", "classification": [], "related_entities": []}, {"description": "Submitted as Committee Bill and Reported Favorably by Appropriations; YEAS 18 NAYS 0", "date": "2026-02-18", "organization_id": "~{\"classification\": \"upper\"}", "classification": [], "related_entities": []}, {"description": "Filed", "date": "2026-02-18", "organization_id": "~{\"classification\": \"upper\"}", "classification": ["filing"], "related_entities": []}, {"description": "Placed on Calendar, on 2nd reading", "date": "2026-02-18", "organization_id": "~{\"classification\": \"upper\"}", "classification": [], "related_entities": []}, {"description": "Placed on Special Order Calendar, 02/20/26", "date": "2026-02-18", "organization_id": "~{\"classification\": \"upper\"}", "classification": [], "related_entities": []}, {"description": "Introduced", "date": "2026-02-19", "organization_id": "~{\"classification\": \"upper\"}", "classification": ["introduction"], "related_entities": []}, {"description": "Read 2nd time", "date": "2026-02-20", "organization_id": "~{\"classification\": \"upper\"}", "classification": ["reading-2"], "related_entities": []}, {"description": "Read 3rd time", "date": "2026-02-20", "organization_id": "~{\"classification\": \"upper\"}", "classification": ["reading-3"], "related_entities": []}, {"description": "Passed; YEAS 36 NAYS 0", "date": "2026-02-20", "organization_id": "~{\"classification\": \"upper\"}", "classification": ["passage"], "related_entities": []}, {"description": "The Senate requests that the House pass the bill as passed by the Senate or agree to include the bill in the Budget Conference", "date": "2026-02-20", "organization_id": "~{\"classification\": \"upper\"}", "classification": [], "related_entities": []}, {"description": "Immediately certified", "date": "2026-02-20", "organization_id": "~{\"classification\": \"upper\"}", "classification": [], "related_entities": []}, {"description": "In Messages", "date": "2026-02-20", "organization_id": "~{\"classification\": \"lower\"}", "classification": [], "related_entities": []}], "sponsorships": [{"name": "Appropriations", "classification": "primary", "entity_type": "organization", "primary": true, "person_id": null, "organization_id": "~{\"name\": \"Appropriations\"}"}], "related_bills": [], "versions": [{"note": "S 2516 pb", "links": [{"url": "https://flsenate.gov/Session/Bill/2026/2516/BillText/pb/HTML", "media_type": "text/html"}, {"url": "https://flsenate.gov/Session/Bill/2026/2516/BillText/pb/PDF", "media_type": "application/pdf"}], "date": "", "classification": ""}, {"note": "S 2516 Filed", "links": [{"url": "https://flsenate.gov/Session/Bill/2026/2516/BillText/Filed/HTML", "media_type": "text/html"}, {"url": "https://flsenate.gov/Session/Bill/2026/2516/BillText/Filed/PDF", "media_type": "application/pdf"}], "date": "", "classification": ""}], "documents": [{"note": "Bill Analysis -- Appropriations (Pre-Meeting) (2/17/2026 9:33 AM)", "links": [{"url": "https://flsenate.gov/Session/Bill/2026/2516/Analyses/2026s02516.pre.ap.PDF", "media_type": "application/pdf"}], "date": "", "classification": ""}, {"note": "Bill Analysis -- Appropriations (Post-Meeting) (2/19/2026 11:00 AM)", "links": [{"url": "https://flsenate.gov/Session/Bill/2026/2516/Analyses/2026s02516.ap.PDF", "media_type": "application/pdf"}], "date": "", "classification": ""}], "citations": [{"publication": "Florida Statues", "citation": "464.0195", "citation_type": "proposed", "effective": null, "expires": null, "url": "https://flsenate.gov/laws/statutes/2025/464.0195"}, {"publication": "Florida Statues", "citation": "1009.26", "citation_type": "proposed", "effective": null, "expires": null, "url": "https://flsenate.gov/laws/statutes/2025/1009.26"}, {"publication": "Florida Statues", "citation": "1009.8962", "citation_type": "proposed", "effective": null, "expires": null, "url": "https://flsenate.gov/laws/statutes/2025/1009.8962"}, {"publication": "Florida Chapter Law", "citation": "2025-199", "citation_type": "chapter", "effective": null, "expires": null, "url": "http://laws.flrules.org/2025/199"}], "sources": [{"url": "https://flsenate.gov/Session/Bill/2026/2516/ByCategory", "note": ""}], "extras": {}, "jurisdiction": {"id": "ocd-jurisdiction/country:us/state:fl/government", "name": "Florida", "classification": "state", "division_id": "ocd-division/country:us/state:fl"}, "scraped_at": "2026-02-24T13:50:48+00:00", "_id": "d58b15f4-1181-11f1-984f-22865c4544ef"}