{"legislative_session": "2026", "identifier": "HB 1539", "title": "Blood Testing Required Following Civilian-involved Shootings", "from_organization": "~{\"classification\": \"lower\"}", "classification": ["bill"], "subject": ["crimes"], "abstracts": [{"note": "summary", "abstract": "Blood Testing Required Following Civilian-involved Shootings;  Requires civilian to submit to test of his or her blood within certain timeframe after incident if he or she discharges firearm within this state resulting in injury or death; specifies procedure for testing; specifies consequences for refusing to submit to testing; provides for confidentiality & disclosure of test results; provides reporting requirements."}], "other_titles": [], "other_identifiers": [], "actions": [{"description": "Filed", "date": "2026-01-09", "organization_id": "~{\"classification\": \"lower\"}", "classification": ["filing"], "related_entities": []}, {"description": "1st Reading (Original Filed Version)", "date": "2026-01-13", "organization_id": "~{\"classification\": \"lower\"}", "classification": ["filing", "reading-1"], "related_entities": []}, {"description": "Referred to Criminal Justice Subcommittee", "date": "2026-01-15", "organization_id": "~{\"classification\": \"lower\"}", "classification": ["referral-committee"], "related_entities": []}, {"description": "Referred to Judiciary Committee", "date": "2026-01-15", "organization_id": "~{\"classification\": \"lower\"}", "classification": ["referral-committee"], "related_entities": []}, {"description": "Now in Criminal Justice Subcommittee", "date": "2026-01-15", "organization_id": "~{\"classification\": \"lower\"}", "classification": [], "related_entities": []}], "sponsorships": [{"name": "Aristide", "classification": "primary", "entity_type": "person", "primary": true, "person_id": "~{\"name\": \"Aristide\"}", "organization_id": null}], "related_bills": [], "versions": [{"note": "H 1539 Filed", "links": [{"url": "https://flsenate.gov/Session/Bill/2026/1539/BillText/Filed/PDF", "media_type": "application/pdf"}], "date": "", "classification": ""}], "documents": [], "citations": [], "sources": [{"url": "https://flsenate.gov/Session/Bill/2026/1539/ByCategory", "note": ""}], "extras": {}, "jurisdiction": {"id": "ocd-jurisdiction/country:us/state:fl/government", "name": "Florida", "classification": "state", "division_id": "ocd-division/country:us/state:fl"}, "scraped_at": "2026-01-22T11:56:26+00:00", "_id": "f4f1d06a-f785-11f0-b5d2-8ebf53432a09"}