{"legislative_session": "2026", "identifier": "SB 424", "title": "Educational Facilities", "from_organization": "~{\"classification\": \"upper\"}", "classification": ["bill"], "subject": ["subject index"], "abstracts": [{"note": "summary", "abstract": "Educational Facilities;  Deleting a provision authorizing a school of hope to colocate with another school in a public school facility; deleting a provision requiring a school district to permit a school of hope to use an underused, vacant, or surplus school district facility; deleting a requirement for students enrolled in a school of hope to be included in the school district\u2019s total capital outlay full-time equivalent membership, etc."}], "other_titles": [], "other_identifiers": [], "actions": [{"description": "Filed", "date": "2025-11-07", "organization_id": "~{\"classification\": \"upper\"}", "classification": ["filing"], "related_entities": []}, {"description": "Referred to Education Pre-K - 12; Appropriations Committee on Pre-K - 12 Education; Fiscal Policy", "date": "2025-11-17", "organization_id": "~{\"classification\": \"upper\"}", "classification": ["referral-committee"], "related_entities": []}, {"description": "Introduced", "date": "2026-01-13", "organization_id": "~{\"classification\": \"upper\"}", "classification": ["introduction"], "related_entities": []}], "sponsorships": [{"name": "Rouson", "classification": "primary", "entity_type": "person", "primary": true, "person_id": "~{\"name\": \"Rouson\"}", "organization_id": null}, {"name": "Osgood", "classification": "cosponsor", "entity_type": "person", "primary": false, "person_id": "~{\"name\": \"Osgood\"}", "organization_id": null}, {"name": "Bracy Davis", "classification": "cosponsor", "entity_type": "person", "primary": false, "person_id": "~{\"name\": \"Bracy Davis\"}", "organization_id": null}], "related_bills": [], "versions": [{"note": "S 424 Filed", "links": [{"url": "https://flsenate.gov/Session/Bill/2026/424/BillText/Filed/HTML", "media_type": "text/html"}, {"url": "https://flsenate.gov/Session/Bill/2026/424/BillText/Filed/PDF", "media_type": "application/pdf"}], "date": "", "classification": ""}], "documents": [], "citations": [{"publication": "Florida Statues", "citation": "1002.333", "citation_type": "proposed", "effective": null, "expires": null, "url": "https://flsenate.gov/laws/statutes/2025/1002.333"}], "sources": [{"url": "https://flsenate.gov/Session/Bill/2026/424/ByCategory", "note": ""}], "extras": {}, "jurisdiction": {"id": "ocd-jurisdiction/country:us/state:fl/government", "name": "Florida", "classification": "state", "division_id": "ocd-division/country:us/state:fl"}, "scraped_at": "2026-02-26T13:06:54+00:00", "_id": "7591ed8a-12f8-11f1-bdb5-ce8b3efe2eed"}