{"legislative_session": "2026", "identifier": "SB 1480", "title": "Temporary Certificates for Practice in Areas of Critical Need", "from_organization": "~{\"classification\": \"upper\"}", "classification": ["bill"], "subject": ["subject index"], "abstracts": [{"note": "summary", "abstract": "Temporary Certificates for Practice in Areas of Critical Need;  Revising the conditions under which the Board of Medicine, the Board of Osteopathic Medicine, and the Board of Nursing, respectively, are authorized to issue temporary certificates for practice in areas of critical need; authorizing certificateholders to continue primary care services after such areas lose their critical need designation under certain circumstances, etc."}], "other_titles": [], "other_identifiers": [], "actions": [{"description": "Filed", "date": "2026-01-08", "organization_id": "~{\"classification\": \"upper\"}", "classification": ["filing"], "related_entities": []}, {"description": "Referred to Health Policy; Appropriations Committee on Health and Human Services; Rules", "date": "2026-01-16", "organization_id": "~{\"classification\": \"upper\"}", "classification": ["referral-committee"], "related_entities": []}, {"description": "On Committee agenda-- Health Policy, 01/26/26, 3:30 pm, 412 Knott Building", "date": "2026-01-21", "organization_id": "~{\"classification\": \"upper\"}", "classification": [], "related_entities": []}, {"description": "Introduced", "date": "2026-01-22", "organization_id": "~{\"classification\": \"upper\"}", "classification": ["introduction"], "related_entities": []}, {"description": "CS by Health Policy; YEAS 9 NAYS 0", "date": "2026-01-26", "organization_id": "~{\"classification\": \"upper\"}", "classification": [], "related_entities": []}, {"description": "Pending reference review under Rule 4.7(2) - (Committee Substitute)", "date": "2026-01-28", "organization_id": "~{\"classification\": \"upper\"}", "classification": [], "related_entities": []}, {"description": "Now in Appropriations Committee on Health and Human Services", "date": "2026-01-28", "organization_id": "~{\"classification\": \"upper\"}", "classification": [], "related_entities": []}, {"description": "CS by Health Policy read 1st time", "date": "2026-01-29", "organization_id": "~{\"classification\": \"upper\"}", "classification": [], "related_entities": []}, {"description": "On Committee agenda-- Appropriations Committee on Health and Human Services, 02/04/26, 1:00 pm, 412 Knott Building", "date": "2026-01-30", "organization_id": "~{\"classification\": \"upper\"}", "classification": [], "related_entities": []}, {"description": "Favorable by Appropriations Committee on Health and Human Services; YEAS 7 NAYS 0", "date": "2026-02-04", "organization_id": "~{\"classification\": \"upper\"}", "classification": ["committee-passage-favorable"], "related_entities": []}, {"description": "Now in Rules", "date": "2026-02-04", "organization_id": "~{\"classification\": \"upper\"}", "classification": [], "related_entities": []}], "sponsorships": [{"name": "Health Policy", "classification": "primary", "entity_type": "organization", "primary": true, "person_id": null, "organization_id": "~{\"name\": \"Health Policy\"}"}, {"name": "Burton", "classification": "primary", "entity_type": "person", "primary": true, "person_id": "~{\"name\": \"Burton\"}", "organization_id": null}], "related_bills": [], "versions": [{"note": "S 1480 Filed", "links": [{"url": "https://flsenate.gov/Session/Bill/2026/1480/BillText/Filed/HTML", "media_type": "text/html"}, {"url": "https://flsenate.gov/Session/Bill/2026/1480/BillText/Filed/PDF", "media_type": "application/pdf"}], "date": "", "classification": ""}, {"note": "S 1480 c1", "links": [{"url": "https://flsenate.gov/Session/Bill/2026/1480/BillText/c1/HTML", "media_type": "text/html"}, {"url": "https://flsenate.gov/Session/Bill/2026/1480/BillText/c1/PDF", "media_type": "application/pdf"}], "date": "", "classification": ""}], "documents": [{"note": "Bill Analysis -- Health Policy (Pre-Meeting) (1/23/2026 3:28 PM)", "links": [{"url": "https://flsenate.gov/Session/Bill/2026/1480/Analyses/2026s01480.pre.hp.PDF", "media_type": "application/pdf"}], "date": "", "classification": ""}, {"note": "Bill Analysis -- Health Policy (Post-Meeting) (1/28/2026 10:00 AM)", "links": [{"url": "https://flsenate.gov/Session/Bill/2026/1480/Analyses/2026s01480.hp.PDF", "media_type": "application/pdf"}], "date": "", "classification": ""}, {"note": "Bill Analysis -- Appropriations Committee on Health and Human Services (Pre-Meeting) (2/3/2026 12:58 PM)", "links": [{"url": "https://flsenate.gov/Session/Bill/2026/1480/Analyses/2026s01480.pre.ahs.PDF", "media_type": "application/pdf"}], "date": "", "classification": ""}, {"note": "Bill Analysis -- Appropriations Committee on Health and Human Services (Post-Meeting) (2/4/2026 3:06 PM)", "links": [{"url": "https://flsenate.gov/Session/Bill/2026/1480/Analyses/2026s01480.ahs.PDF", "media_type": "application/pdf"}], "date": "", "classification": ""}, {"note": "755302 - Amendment (Delete All) to S 1480 Filed", "links": [{"url": "https://flsenate.gov/Session/Bill/2026/1480/Amendment/755302/HTML", "media_type": "text/html"}, {"url": "https://flsenate.gov/Session/Bill/2026/1480/Amendment/755302/PDF", "media_type": "application/pdf"}], "date": "", "classification": ""}], "citations": [{"publication": "Florida Statues", "citation": "458.315", "citation_type": "proposed", "effective": null, "expires": null, "url": "https://flsenate.gov/laws/statutes/2025/458.315"}, {"publication": "Florida Statues", "citation": "459.0076", "citation_type": "proposed", "effective": null, "expires": null, "url": "https://flsenate.gov/laws/statutes/2025/459.0076"}, {"publication": "Florida Statues", "citation": "464.0121", "citation_type": "proposed", "effective": null, "expires": null, "url": "https://flsenate.gov/laws/statutes/2025/464.0121"}], "sources": [{"url": "https://flsenate.gov/Session/Bill/2026/1480/ByCategory", "note": ""}], "extras": {}, "jurisdiction": {"id": "ocd-jurisdiction/country:us/state:fl/government", "name": "Florida", "classification": "state", "division_id": "ocd-division/country:us/state:fl"}, "scraped_at": "2026-02-08T13:03:07+00:00", "_id": "55d9495e-04e6-11f1-ac39-7a98db051692"}