{"legislative_session": "2026", "identifier": "SB 1340", "title": "Coordinated Screening and Progress Monitoring", "from_organization": "~{\"classification\": \"upper\"}", "classification": ["bill"], "subject": ["k"], "abstracts": [{"note": "summary", "abstract": "Coordinated Screening and Progress Monitoring;  Specifying requirements for a school district if a student exhibits characteristics of dyslexia or dyscalculia; providing circumstances under which a student is required to undergo further screening for dyslexia or dyscalculia, etc."}], "other_titles": [], "other_identifiers": [], "actions": [{"description": "Filed", "date": "2026-01-07", "organization_id": "~{\"classification\": \"upper\"}", "classification": ["filing"], "related_entities": []}, {"description": "Referred to Education Pre-K - 12; Appropriations Committee on Health and Human Services; Rules", "date": "2026-01-16", "organization_id": "~{\"classification\": \"upper\"}", "classification": ["referral-committee"], "related_entities": []}, {"description": "On Committee agenda-- Education Pre-K - 12, 01/27/26, 3:30 pm, 412 Knott Building", "date": "2026-01-22", "organization_id": "~{\"classification\": \"upper\"}", "classification": [], "related_entities": []}, {"description": "Introduced", "date": "2026-01-22", "organization_id": "~{\"classification\": \"upper\"}", "classification": ["introduction"], "related_entities": []}, {"description": "Favorable by Education Pre-K - 12; YEAS 5 NAYS 0", "date": "2026-01-27", "organization_id": "~{\"classification\": \"upper\"}", "classification": ["committee-passage-favorable"], "related_entities": []}, {"description": "Now in Appropriations Committee on Health and Human Services", "date": "2026-01-27", "organization_id": "~{\"classification\": \"upper\"}", "classification": [], "related_entities": []}], "sponsorships": [{"name": "Harrell", "classification": "primary", "entity_type": "person", "primary": true, "person_id": "~{\"name\": \"Harrell\"}", "organization_id": null}], "related_bills": [], "versions": [{"note": "S 1340 Filed", "links": [{"url": "https://flsenate.gov/Session/Bill/2026/1340/BillText/Filed/HTML", "media_type": "text/html"}, {"url": "https://flsenate.gov/Session/Bill/2026/1340/BillText/Filed/PDF", "media_type": "application/pdf"}], "date": "", "classification": ""}], "documents": [{"note": "Bill Analysis -- Education Pre-K - 12 (Pre-Meeting) (1/26/2026 3:30 PM)", "links": [{"url": "https://flsenate.gov/Session/Bill/2026/1340/Analyses/2026s01340.pre.ed.PDF", "media_type": "application/pdf"}], "date": "", "classification": ""}, {"note": "Bill Analysis -- Education Pre-K - 12 (Post-Meeting) (1/27/2026 4:52 PM)", "links": [{"url": "https://flsenate.gov/Session/Bill/2026/1340/Analyses/2026s01340.ed.PDF", "media_type": "application/pdf"}], "date": "", "classification": ""}], "citations": [{"publication": "Florida Statues", "citation": "1008.25", "citation_type": "proposed", "effective": null, "expires": null, "url": "https://flsenate.gov/laws/statutes/2025/1008.25"}], "sources": [{"url": "https://flsenate.gov/Session/Bill/2026/1340/ByCategory", "note": ""}], "extras": {}, "jurisdiction": {"id": "ocd-jurisdiction/country:us/state:fl/government", "name": "Florida", "classification": "state", "division_id": "ocd-division/country:us/state:fl"}, "scraped_at": "2026-01-31T12:14:31+00:00", "_id": "d07a4ac8-fe97-11f0-a93d-ce2a7d54be4b"}