{"legislative_session": "2026", "identifier": "HB 781", "title": "Medicaid Coverage of Blood Pressure Monitors and Cuffs", "from_organization": "~{\"classification\": \"lower\"}", "classification": ["bill"], "subject": ["subject index"], "abstracts": [{"note": "summary", "abstract": "Medicaid Coverage of Blood Pressure Monitors and Cuffs;  Defines \"blood pressure monitor & cuff;\" requiring AHCA to provide coverage for blood pressure monitors & cuffs under Medicaid pharmacy benefit for certain persons; provides requirements for coverage; provides that coverage of blood pressure monitors & cuffs includes cost of any necessary repairs or replacement parts; provides coverage qualification requirements for Medicaid recipients; requires agency to seek federal approval for implementation of coverage & to include rate impact in Medicaid managed medical assistance program & long-term care managed care program rates beginning on specified date."}], "other_titles": [], "other_identifiers": [], "actions": [{"description": "Filed", "date": "2025-12-16", "organization_id": "~{\"classification\": \"lower\"}", "classification": ["filing"], "related_entities": []}, {"description": "Referred to Health Care Facilities & Systems Subcommittee", "date": "2026-01-05", "organization_id": "~{\"classification\": \"lower\"}", "classification": ["referral-committee"], "related_entities": []}, {"description": "Referred to Health Care Budget Subcommittee", "date": "2026-01-05", "organization_id": "~{\"classification\": \"lower\"}", "classification": ["referral-committee"], "related_entities": []}, {"description": "Referred to Health & Human Services Committee", "date": "2026-01-05", "organization_id": "~{\"classification\": \"lower\"}", "classification": ["referral-committee"], "related_entities": []}, {"description": "Now in Health Care Facilities & Systems Subcommittee", "date": "2026-01-05", "organization_id": "~{\"classification\": \"lower\"}", "classification": [], "related_entities": []}, {"description": "1st Reading (Original Filed Version)", "date": "2026-01-13", "organization_id": "~{\"classification\": \"lower\"}", "classification": ["filing", "reading-1"], "related_entities": []}], "sponsorships": [{"name": "Hodgers", "classification": "primary", "entity_type": "person", "primary": true, "person_id": "~{\"name\": \"Hodgers\"}", "organization_id": null}], "related_bills": [], "versions": [{"note": "H 781 Filed", "links": [{"url": "https://flsenate.gov/Session/Bill/2026/781/BillText/Filed/PDF", "media_type": "application/pdf"}], "date": "", "classification": ""}], "documents": [], "citations": [], "sources": [{"url": "https://flsenate.gov/Session/Bill/2026/781/ByCategory", "note": ""}], "extras": {}, "jurisdiction": {"id": "ocd-jurisdiction/country:us/state:fl/government", "name": "Florida", "classification": "state", "division_id": "ocd-division/country:us/state:fl"}, "scraped_at": "2026-01-20T11:21:49+00:00", "_id": "b5c0fd2c-f5e5-11f0-838b-721896711826"}