{"identifier": "", "motion_text": "Favorable (State Affairs Committee)", "motion_classification": ["committee-passage"], "start_date": "2026-01-27T09:30:00-05:00", "result": "pass", "organization": "~{\"classification\": \"lower\"}", "legislative_session": "2026", "bill": "ff481aa8-8789-11f1-938d-4aedfba1e072", "bill_action": null, "bill_identifier": "HB 31", "votes": [], "counts": [{"option": "yes", "value": 20}, {"option": "no", "value": 4}, {"option": "not voting", "value": 2}], "sources": [{"url": "https://flhouse.gov/Sections/Committees/billvote.aspx?VoteId=75500&IsPCB=0&BillId=82564&", "note": ""}], "extras": {}, "_id": "06a13618-878a-11f1-938d-4aedfba1e072"}